bottle_apispec/__init__.py
bottle_apispec-0.9.0.dist-info/LICENSE
bottle_apispec-0.9.0.dist-info/METADATA
bottle_apispec-0.9.0.dist-info/WHEEL
bottle_apispec-0.9.0.dist-info/top_level.txt
bottle_apispec-0.9.0.dist-info/RECORD
