Metadata-Version: 2.1
Name: bottle-apispec
Version: 0.9.0
Summary: Bottle + APISpec + Marshmallow integration
Home-page: https://gitlab.com/TruckPad/utils/bottle-apispec
Author: Marcos Araujo Sobrinho
Author-email: marcos.sobrinho@truckpad.com.br
License: UNKNOWN
Platform: UNKNOWN
Classifier: Development Status :: 2 - Pre-Alpha
Classifier: Operating System :: POSIX
Classifier: Programming Language :: Python :: 3
Classifier: Topic :: Internet :: WWW/HTTP
Requires-Dist: apispec (<4)
Requires-Dist: bottle (>=0.12.0)
Requires-Dist: marshmallow (>=2.10.0)
